jupyterlab_materialdarker/__init__.py
jupyterlab_materialdarker/_version.py
jupyterlab_materialdarker/labextension/build_log.json
jupyterlab_materialdarker/labextension/package.json
jupyterlab_materialdarker/labextension/static/lib_index_js.700af17e219c6d55c7a5.js
jupyterlab_materialdarker/labextension/static/lib_index_js.700af17e219c6d55c7a5.js.map
jupyterlab_materialdarker/labextension/static/lib_index_js.ca9703ee903f6db6fc8a.js
jupyterlab_materialdarker/labextension/static/lib_index_js.ca9703ee903f6db6fc8a.js.map
jupyterlab_materialdarker/labextension/static/remoteEntry.1b64e15439925750fe30.js
jupyterlab_materialdarker/labextension/static/remoteEntry.1b64e15439925750fe30.js.map
jupyterlab_materialdarker/labextension/static/remoteEntry.26f3eeb62bb7b3fd19b2.js.map
jupyterlab_materialdarker/labextension/static/style.js
jupyterlab_materialdarker/labextension/themes/jupyterlab_materialdarker/index.css
jupyterlab_materialdarker/labextension/themes/jupyterlab_materialdarker/index.js
jupyterlab_materialdarker-0.8.0.data/data/share/jupyter/labextensions/jupyterlab_materialdarker/build_log.json
jupyterlab_materialdarker-0.8.0.data/data/share/jupyter/labextensions/jupyterlab_materialdarker/package.json
jupyterlab_materialdarker-0.8.0.data/data/share/jupyter/labextensions/jupyterlab_materialdarker/static/lib_index_js.700af17e219c6d55c7a5.js
jupyterlab_materialdarker-0.8.0.data/data/share/jupyter/labextensions/jupyterlab_materialdarker/static/lib_index_js.700af17e219c6d55c7a5.js.map
jupyterlab_materialdarker-0.8.0.data/data/share/jupyter/labextensions/jupyterlab_materialdarker/static/lib_index_js.ca9703ee903f6db6fc8a.js
jupyterlab_materialdarker-0.8.0.data/data/share/jupyter/labextensions/jupyterlab_materialdarker/static/lib_index_js.ca9703ee903f6db6fc8a.js.map
jupyterlab_materialdarker-0.8.0.data/data/share/jupyter/labextensions/jupyterlab_materialdarker/static/remoteEntry.1b64e15439925750fe30.js
jupyterlab_materialdarker-0.8.0.dist-info/METADATA
jupyterlab_materialdarker-0.8.0.dist-info/WHEEL
jupyterlab_materialdarker-0.8.0.dist-info/licenses/LICENSE
jupyterlab_materialdarker-0.8.0.dist-info/RECORD
