Metadata-Version: 2.4
Name: jupyterlab_materialdarker
Version: 0.8.0
Summary: The Material Darker theme for JupyterLab.
Project-URL: Homepage, https://github.com/oriolmirosa/jupyterlab_materialdarker
Project-URL: Bug Tracker, https://github.com/oriolmirosa/jupyterlab_materialdarker/issues
Project-URL: Repository, https://github.com/oriolmirosa/jupyterlab_materialdarker.git
Author-email: Oriol Mirosa <oriolmirosa@gmail.com>
License: BSD 3-Clause License
License-File: LICENSE
Keywords: jupyter,jupyterlab,jupyterlab-extension
Classifier: Framework :: Jupyter
Classifier: Framework :: Jupyter :: JupyterLab
Classifier: Framework :: Jupyter :: JupyterLab :: 4
Classifier: Framework :: Jupyter :: JupyterLab :: Extensions
Classifier: Framework :: Jupyter :: JupyterLab :: Extensions :: Prebuilt
Classifier: Framework :: Jupyter :: JupyterLab :: Extensions :: Themes
Classifier: License :: OSI Approved :: BSD License
Classifier: Programming Language :: Python
Classifier: Programming Language :: Python :: 3
Classifier: Programming Language :: Python :: 3.9
Classifier: Programming Language :: Python :: 3.10
Classifier: Programming Language :: Python :: 3.11
Classifier: Programming Language :: Python :: 3.12
Classifier: Programming Language :: Python :: 3.13
Classifier: Programming Language :: Python :: 3.14
Requires-Python: >=3.9
Requires-Dist: jupyterlab>=4.5.1
